qualpy
