Metadata-Version: 1.1
Name: qualpy
Version: 0.3.5
Summary: your qualtrics buddy
Home-page: https://github.com/3nth/qualpy
Author: Derek Flenniken
Author-email: derek.flenniken@ucsf.edu
License: MIT License
Download-URL: https://github.com/3nth/qualpy
Platform: any
Classifier: Programming Language :: Python
Classifier: Development Status :: 4 - Beta
Classifier: Natural Language :: English
Classifier: Environment :: Console
Classifier: Intended Audience :: Developers
Classifier: License :: OSI Approved :: MIT License
Classifier: Operating System :: OS Independent
Classifier: Topic :: Software Development :: Libraries :: Python Modules
